README.md
setup.py
mbc.egg-info/PKG-INFO
mbc.egg-info/SOURCES.txt
mbc.egg-info/dependency_links.txt
mbc.egg-info/requires.txt
mbc.egg-info/top_level.txt
moonlistclient/__init__.py
moonlistclient/client.py
moonlistclient/exceptions.py
moonlistclient/http.py
moonlistclient/schemas.py
moonlistclient/webhook_manager.py