Metadata-Version: 2.1
Name: mbc
Version: 0.5
Summary: Wrapper for the moonlist api
Home-page: https://github.com/VadyChel/MoonlistClient
Author-email: zyzel19@gmail.com
License: UNKNOWN
Platform: UNKNOWN
Classifier: Programming Language :: Python :: 3
Classifier: License :: OSI Approved :: GNU Affero General Public License v3
Classifier: Operating System :: OS Independent
